circular_import_detector/__init__.py
circular_import_detector/__main__.py
circular_import_detector/circular_import_detector.py
circular_import_detector/example_usage.py
circular_import_detector/precommit_hook.py
circular_import_detector/test_circular_imports.py
circular_import_detector-1.0.16.dist-info/licenses/LICENSE
circular_import_detector-1.0.16.dist-info/METADATA
circular_import_detector-1.0.16.dist-info/WHEEL
circular_import_detector-1.0.16.dist-info/entry_points.txt
circular_import_detector-1.0.16.dist-info/top_level.txt
circular_import_detector-1.0.16.dist-info/RECORD
