Metadata-Version: 2.4
Name: circular-import-detector
Version: 1.0.16
Summary: A tool to detect circular imports in Python projects
Author-email: Paul Nilsson <Paul.Nilsson@cern.ch>
Project-URL: Homepage, https://github.com/PalNilsson/circular-import-detector
Project-URL: Repository, https://github.com/PalNilsson/circular-import-detector.git
Project-URL: Issues, https://github.com/PalNilsson/circular-import-detector/issues
Classifier: Development Status :: 4 - Beta
Classifier: Intended Audience :: Developers
Classifier: License :: OSI Approved :: MIT License
Classifier: Programming Language :: Python :: 3
Classifier: Programming Language :: Python :: 3.7
Classifier: Programming Language :: Python :: 3.8
Classifier: Programming Language :: Python :: 3.9
Classifier: Programming Language :: Python :: 3.10
Classifier: Programming Language :: Python :: 3.11
Classifier: Programming Language :: Python :: 3.12
Classifier: Topic :: Software Development :: Quality Assurance
Classifier: Topic :: Software Development :: Testing
Requires-Python: >=3.7
License-File: LICENSE
Dynamic: license-file
